smartexecutorlib/__init__.py
smartexecutorlib/executors.py
smartexecutorlib-0.1.1.dist-info/licenses/LICENSE
smartexecutorlib-0.1.1.dist-info/METADATA
smartexecutorlib-0.1.1.dist-info/WHEEL
smartexecutorlib-0.1.1.dist-info/top_level.txt
smartexecutorlib-0.1.1.dist-info/RECORD
