Metadata-Version: 2.4
Name: smartexecutorlib
Version: 0.1.1
Summary: Smart executors.
Home-page: https://github.com/smartlegionlab/smartexecutorlib/
Author: A.A. Suvorov
Author-email: smartlegiondev@gmail.com
License: BSD 3-Clause License
Project-URL: Documentation, https://github.com/smartlegionlab/smartexecutorlib/blob/master/README.md
Project-URL: Release notes, https://github.com/smartlegionlab/smartexecutorlib/releases
Keywords: executor,executors,command executor,smartlegionlab
Classifier: Development Status :: 5 - Production/Stable
Classifier: License :: OSI Approved :: BSD License
Classifier: Natural Language :: English
Classifier: Operating System :: OS Independent
Classifier: Operating System :: POSIX :: Linux
Classifier: Programming Language :: Python :: 3 :: Only
Classifier: Topic :: Software Development :: Libraries :: Python Modules
Requires-Python: >=3.6
License-File: LICENSE
Dynamic: license-file
